pypm/__init__.py
pypm/cli.py
pypm/errors.py
pypm/generator.py
pypm/main.py
pypm/post_operations.py
pypm/setup.py
pypm/version.py
pypm/data/pkg.json
pypm/data/pyproject.toml
pypm/data/setup.cfg
pypm/data/setup.py
pypm2-0.2.0.data/data/data_files/pkg.json
pypm2-0.2.0.data/data/data_files/pyproject.toml
pypm2-0.2.0.data/data/data_files/setup.cfg
pypm2-0.2.0.data/data/data_files/setup.py
pypm2-0.2.0.dist-info/METADATA
pypm2-0.2.0.dist-info/WHEEL
pypm2-0.2.0.dist-info/entry_points.txt
pypm2-0.2.0.dist-info/top_level.txt
pypm2-0.2.0.dist-info/RECORD
