Metadata-Version: 2.1
Name: pypm2
Version: 0.2.0
Summary: Python package manager for projects running Python3.6 and above.
Home-page: https://github.com/ableinc/pypm
Author: AbleInc
Author-email: douglas.jaylen@gmail.com
License: ISC
Keywords: package manager,dependency manager,manager,python 3,cli tool,command line tool
Platform: UNKNOWN
Classifier: Programming Language :: Python :: 3
Classifier: License :: OSI Approved :: MIT License
Classifier: Operating System :: OS Independent
Requires-Dist: Click (==7.0)
Requires-Dist: stdlib-list (==0.7.0)
